imumocap/__init__.py
imumocap/joint.py
imumocap/link.py
imumocap/matrix.py
imumocap/plot.py
imumocap/pose.py
imumocap/file/__init__.py
imumocap/file/load.py
imumocap/file/save.py
imumocap/solvers/__init__.py
imumocap/solvers/calibrate.py
imumocap/solvers/floor.py
imumocap/solvers/interpolate.py
imumocap/solvers/translate.py
imumocap/viewer/__init__.py
imumocap/viewer/connection.py
imumocap/viewer/primatives.py
imumocap-1.3.0.dist-info/licenses/LICENSE.md
imumocap-1.3.0.dist-info/METADATA
imumocap-1.3.0.dist-info/WHEEL
imumocap-1.3.0.dist-info/top_level.txt
imumocap-1.3.0.dist-info/RECORD
