Metadata-Version: 2.4
Name: imumocap
Version: 1.3.0
Summary: IMU Mocap
Author-email: x-io Technologies Limited <info@x-io.co.uk>
License: 
Project-URL: Repository, https://github.com/xioTechnologies/IMU-Mocap
License-File: LICENSE.md
Dynamic: license-file
